unavailable_object/__init__.py
unavailable_object/_version.py
unavailable_object-0.0.2.dist-info/LICENSE
unavailable_object-0.0.2.dist-info/METADATA
unavailable_object-0.0.2.dist-info/WHEEL
unavailable_object-0.0.2.dist-info/top_level.txt
unavailable_object-0.0.2.dist-info/RECORD
